tab_transformer_pytorch/__init__.py
tab_transformer_pytorch/ft_transformer.py
tab_transformer_pytorch/tab_transformer_pytorch.py
tab_transformer_pytorch-0.6.1.dist-info/licenses/LICENSE
tab_transformer_pytorch-0.6.1.dist-info/METADATA
tab_transformer_pytorch-0.6.1.dist-info/WHEEL
tab_transformer_pytorch-0.6.1.dist-info/top_level.txt
tab_transformer_pytorch-0.6.1.dist-info/RECORD
