Metadata-Version: 2.4
Name: tab-transformer-pytorch
Version: 0.6.1
Summary: Tab Transformer - Pytorch
Home-page: https://github.com/lucidrains/tab-transformer-pytorch
Author: Phil Wang
Author-email: lucidrains@gmail.com
License: MIT
Keywords: artificial intelligence,transformers,attention mechanism,tabular data
Classifier: Development Status :: 4 - Beta
Classifier: Intended Audience :: Developers
Classifier: Topic :: Scientific/Engineering :: Artificial Intelligence
Classifier: License :: OSI Approved :: MIT License
Classifier: Programming Language :: Python :: 3.6
License-File: LICENSE
Requires-Dist: einops>=0.8
Requires-Dist: discrete-continuous-embed-readout>=0.0.32
Requires-Dist: hyper-connections>=0.3.12
Requires-Dist: torch>=2.3
Requires-Dist: x-mlps-pytorch
Dynamic: author
Dynamic: author-email
Dynamic: classifier
Dynamic: description-content-type
Dynamic: home-page
Dynamic: keywords
Dynamic: license
Dynamic: license-file
Dynamic: requires-dist
Dynamic: summary
